version_finder_gui/__init__.py
version_finder_gui/__version__.py
version_finder_gui/gui.py
version_finder_gui/widgets.py
version_finder_gui/assets/icon.png
version_finder_git_based_versions_gui_app-2.3.4.dist-info/LICENSE
version_finder_git_based_versions_gui_app-2.3.4.dist-info/METADATA
version_finder_git_based_versions_gui_app-2.3.4.dist-info/WHEEL
version_finder_git_based_versions_gui_app-2.3.4.dist-info/entry_points.txt
version_finder_git_based_versions_gui_app-2.3.4.dist-info/top_level.txt
version_finder_git_based_versions_gui_app-2.3.4.dist-info/RECORD
