Metadata-Version: 2.2
Name: version-finder-git-based-versions-gui-app
Version: 2.3.4
Summary: An App for finding versions in Git repositories
Home-page: https://github.com/LevyMatan/version_finder
Author: Matan Levy
License: MIT
Requires-Python: >=3.7
License-File: LICENSE
Requires-Dist: version-finder-git-based-versions>=7.0.1
Requires-Dist: customtkinter>=5.0.0
Requires-Dist: pillow>=9.0.0
Provides-Extra: dev
Requires-Dist: pytest; extra == "dev"
Requires-Dist: pytest-xdist; extra == "dev"
Requires-Dist: pytest-cov; extra == "dev"
Requires-Dist: flake8; extra == "dev"
Requires-Dist: autopep8; extra == "dev"
Dynamic: author
Dynamic: description
Dynamic: description-content-type
Dynamic: home-page
Dynamic: license
Dynamic: provides-extra
Dynamic: requires-dist
Dynamic: requires-python
Dynamic: summary
